MANIFEST.in
README.org
setup.py
test.sh
tlsauth.py
tlsauth.egg-info/PKG-INFO
tlsauth.egg-info/SOURCES.txt
tlsauth.egg-info/dependency_links.txt
tlsauth.egg-info/requires.txt
tlsauth.egg-info/top_level.txt