Metadata-Version: 1.1
Name: tlsauth
Version: 0.4-1
Summary: Implements TLS Authentication - simple client certificate CA inclusive
Home-page: https://pypi.python.org/pypi/tlsauth
Author: Stefan Marsiske
Author-email: s@ctrlc.hu
License: BSD
Keywords: crypto authentication TLS certificate x509 CA
Platform: UNKNOWN
Classifier: Development Status :: 4 - Beta
Classifier: License :: OSI Approved :: BSD License
Classifier: Topic :: Security :: Cryptography
Classifier: Environment :: Web Environment
